Workbook

Sheet Model
B3: Vinci SA (DG FP) - BBG GAAP
A5: x | B5: In Millions of EUR except Per Share | C5: FY 2017 | D5: FY 2018 | E5: FY 2019 | F5: FY 2020 | G5: FY 2021 | H5: FY 2022 | I5: FY 2023 | J5: FY 2024 Est | K5: FY 2025 Est | L5: FY 2026 Est | M5: FY 2027 Est | N5: FY 2028 Est
B6: 12 Months Ending | C6: 12/31/2017 | D6: 12/31/2018 | E6: 12/31/2019 | F6: 12/31/2020 | G6: 12/31/2021 | H6: 12/31/2022 | I6: 12/31/2023 | J6: 12/31/2024 | K6: 12/31/2025
B7: Revenue | C7: 40876 | D7: 44152 | E7: 48752 | F7: 43930 | G7: 49982 | H7: 62265 | I7: 69618 | J7: ='Segment Rev+OPI build'!AI54 -> 72017.38 | K7: ='Segment Rev+OPI build'!AJ54 -> 74942.957 | L7: ='Segment Rev+OPI build'!AK54 -> 78102.056 | M7: ='Segment Rev+OPI build'!AL54 -> 81410.793 | N7: ='Segment Rev+OPI build'!AM54 -> 84877.136
B8: + Sales & Services Revenue | C8: 40876 | D8: 44152 | E8: 48053 | F8: 43234 | G8: 49396 | H8: 61675 | I8: 68838
B9: + Other Revenue | C9: — | D9: — | E9: 699 | F9: 696 | G9: 586 | H9: 590 | I9: 780
B10: + Other Operating Income | C10: 200 | D10: 202 | E10: 198 | F10: 188 | G10: 248 | H10: 249 | I10: 267
B11: - Operating Expenses | C11: 36672 | D11: 39522 | E11: 43498 | F11: 41513 | G11: 45805 | H11: 56048 | I11: 61926
B12: + Research & Development | C12: 0 | D12: 0 | E12: 0 | F12: 0 | G12: 0 | H12: 0 | I12: 0
B13: + Other Operating Expense | C13: 36672 | D13: 39522 | E13: 43498 | F13: 41513 | G13: 45805 | H13: 56048 | I13: 61926
B14: Operating Income (Loss) | C14: 4404 | D14: 4832 | E14: 5452 | F14: 2605 | G14: 4425 | H14: 6466 | I14: 7959 | J14: ='Segment Rev+OPI build'!AH56 -> 8357 | K14: ='Segment Rev+OPI build'!AI56 -> 8760.1266 | L14: ='Segment Rev+OPI build'!AJ56 -> 9153.3751 | M14: ='Segment Rev+OPI build'!AK56 -> 9570.8023 | N14: ='Segment Rev+OPI build'!AL56 -> 10009.934
B15: - Non-Operating (Income) Loss | C15: 296 | D15: 357 | E15: 410 | F15: 781 | G15: 605 | H15: 313 | I15: 940 | J15: =SUM(J16:J21) -> 818.986 | K15: =SUM(K16:K21) -> 833.96405 | L15: =SUM(L16:L21) -> 845.77186 | M15: =SUM(M16:M21) -> 884.34213 | N15: =SUM(N16:N21) -> 924.91789
B16: + Interest Expense, Net | C16: 597 | D16: 606 | E16: 753 | F16: 776 | G16: 766 | H16: 719 | I16: 743 | J16: =J157 -> 818.986 | K16: =K157 -> 833.96405 | L16: =L157 -> 845.77186 | M16: =M157 -> 884.34213 | N16: =N157 -> 924.91789
B17: + Interest Expense | C17: 653 | D17: 635 | E17: 794 | F17: 796 | G17: 767 | H17: 839 | I17: 1205
B18: - Interest Income | C18: 56 | D18: 29 | E18: 41 | F18: 20 | G18: 1 | H18: 120 | I18: 462
B19: + Foreign Exch (Gain) Loss | C19: 11 | D19: 9 | E19: -8 | F19: 15 | G19: -66 | H19: -43 | I19: 119 | J19: 0 | K19: 0 | L19: 0 | M19: 0 | N19: 0
B20: + (Income) Loss from Affiliates | C20: -146 | D20: -88 | E20: -212 | F20: 146 | G20: -12 | H20: -22 | I20: -111 | J20: 0 | K20: 0 | L20: 0 | M20: 0 | N20: 0
B21: + Other Non-Op (Income) Loss | C21: -166 | D21: -170 | E21: -123 | F21: -156 | G21: -83 | H21: -341 | I21: 189 | J21: 0 | K21: 0 | L21: 0 | M21: 0 | N21: 0
B22: Pretax Income | C22: 4108 | D22: 4475 | E22: 5042 | F22: 1824 | G22: 3820 | H22: 6153 | I22: =I14-I15 -> 7019 | J22: =J14-J15 -> 7538.014 | K22: =K14-K15 -> 7926.1625 | L22: =L14-L15 -> 8307.6033 | M22: =M14-M15 -> 8686.4602 | N22: =N14-N15 -> 9085.0159
B23: - Income Tax Expense (Benefit) | C23: 1271 | D23: 1418 | E23: 1634 | F23: 807 | G23: 1625 | H23: 1737 | I23: 1917 | J23: =J306 -> 2110.6439 | K23: =K306 -> 2219.3255 | L23: =L306 -> 2326.1289 | M23: =M306 -> 2432.2088 | N23: =N306 -> 2543.8045
B24: + Current Income Tax | C24: 1537 | D24: 1529 | E24: 1791 | F24: 844 | G24: 1509 | H24: 1809 | I24: 2332
B25: + Deferred Income Tax | C25: -266 | D25: -111 | E25: -157 | F25: -37 | G25: 116 | H25: -72 | I25: -415
B26: Income (Loss) from Cont Ops | C26: 2837 | D26: 3057 | E26: 3408 | F26: 1017 | G26: 2195 | H26: 4416 | I26: 5102 | J26: =J22-J23 -> 5427.3701 | K26: =K22-K23 -> 5706.837 | L26: =L22-L23 -> 5981.4743 | M26: =M22-M23 -> 6254.2513 | N26: =N22-N23 -> 6541.2115
B27: - Net Extraordinary Losses (Gains) | C27: 0 | D27: 0 | E27: 0 | F27: 0 | G27: 0 | H27: 0 | I27: 0 | J27: 0 | K27: 0 | L27: 0 | M27: 0 | N27: 0
B28: + Discontinued Operations | C28: 0 | D28: 0 | E28: 0 | F28: 0 | G28: 0 | H28: 0 | I28: 0 | J28: 0 | K28: 0 | L28: 0 | M28: 0 | N28: 0
B29: + XO & Accounting Changes | C29: 0 | D29: 0 | E29: 0 | F29: 0 | G29: 0 | H29: 0 | I29: 0 | J29: 0 | K29: 0 | L29: 0 | M29: 0 | N29: 0
B30: Income (Loss) Incl. MI | C30: 2837 | D30: 3057 | E30: 3408 | F30: 1017 | G30: 2195 | H30: 4416 | I30: 5102 | J30: =J26-SUM(J27:J29) -> 5427.3701 | K30: =K26-SUM(K27:K29) -> 5706.837 | L30: =L26-SUM(L27:L29) -> 5981.4743 | M30: =M26-SUM(M27:M29) -> 6254.2513 | N30: =N26-SUM(N27:N29) -> 6541.2115
B31: - Minority Interest | C31: 90 | D31: 74 | E31: 148 | F31: -226 | G31: -402 | H31: 157 | I31: 400 | J31: 400 | K31: 400 | L31: 400 | M31: 400 | N31: 401
B32: Net Income, GAAP | C32: 2747 | D32: 2983 | E32: 3260 | F32: 1243 | G32: 2597 | H32: 4259 | I32: 4702 | J32: =J30-J31 -> 5027.3701 | K32: =K30-K31 -> 5306.837 | L32: =L30-L31 -> 5581.4743 | M32: =M30-M31 -> 5854.2513 | N32: =N30-N31 -> 6140.2115
B33: - Preferred Dividends | C33: 0 | D33: 0 | E33: 0 | F33: 0 | G33: 0 | H33: 0 | I33: 0 | J33: 0 | K33: 0 | L33: 0 | M33: 0 | N33: 0
B34: - Other Adjustments | C34: 0 | D34: 0 | E34: 0 | F34: 0 | G34: 0 | H34: 0 | I34: 0 | J34: 0 | K34: 0 | L34: 0 | M34: 0 | N34: 0
B35: Net Income Avail to Common, GAAP | C35: 2747 | D35: 2983 | E35: 3260 | F35: 1243 | G35: 2597 | H35: 4259 | I35: 4702 | J35: =J32-SUM(J33:J34) -> 5027.3701 | K35: =K32-SUM(K33:K34) -> 5306.837 | L35: =L32-SUM(L33:L34) -> 5581.4743 | M35: =M32-SUM(M33:M34) -> 5854.2513 | N35: =N32-SUM(N33:N34) -> 6140.2115
B51: Reference Items
B52: Accounting Standard | C52: IAS/IFRS | D52: IAS/IFRS | E52: IAS/IFRS | F52: IAS/IFRS | G52: IAS/IFRS | H52: IAS/IFRS | I52: IAS/IFRS
B53: EBITDA | C53: 6532 | D53: 7074 | E53: 8492 | F53: 5776 | G53: 7644 | H53: 10079 | I53: 11758 | J53: 12462.938 | K53: 13116.188
B54: EBITDA Margin (T12M) | C54: 15.98 | D54: 16.0219 | E54: 17.4188 | F54: 13.1482 | G54: 15.2935 | H54: 16.1873 | I54: 16.8893 | J54: 17.335475 | K54: 17.656537
B55: EBITA | C55: 5547 | D55: 6149 | E55: 6844 | F55: 4000 | G55: 5858 | H55: 8136 | I55: 9771
B56: EBIT | C56: 4404 | D56: 4832 | E56: 5452 | F56: 2605 | G56: 4425 | H56: 6466 | I56: 7959 | J56: 8613.059 | K56: 9088.471
B57: Operating Margin | C57: 10.774 | D57: 10.944 | E57: 11.1831 | F57: 5.9299 | G57: 8.8532 | H57: 10.3846 | I57: 11.4324 | J57: 11.980439 | K57: 12.23457
B58: Profit Margin | C58: 6.7203 | D58: 6.7562 | E58: 6.6869 | F58: 2.8295 | G58: 5.1959 | H58: 6.8401 | I58: 6.754 | J58: 6.8648891 | K58: 7.1031516
B59: Sales per Employee | C59: 212583.6 | D59: 215612.26 | E59: 222340.8 | F59: 200227.89 | G59: 228678.36 | H59: 232332.09 | I59: 249146.46
B60: Dividends per Share | C60: 2.45 | D60: 2.67 | E60: 2.04 | F60: 2.04 | G60: 2.9 | H60: 4 | I60: 4.5 | J60: 4.764 | K60: 5.139
B61: Total Cash Common Dividends | C61: 1360 | D61: 1481.2262 | E61: 1131.6818 | F61: 1146.6059 | G61: 1645.9837 | H61: 2254.3861 | I61: 2568.6446
B62: Capitalized Interest Expense | C62: 86 | D62: 56 | E62: 0 | F62: — | G62: — | H62: — | I62: —
B63: Personnel Expenses | C63: 10955 | D63: 11999 | E63: 11836 | F63: 11642 | G63: 12488 | H63: 14979 | I63: 16352
B64: Depreciation Expense | C64: 2128 | D64: 22424 | E64: 3040 | F64: 3171 | G64: 3219 | H64: 3613 | I64: 3799
A67: x | B67: In Millions of EUR except Per Share | C67: FY 2017 | D67: FY 2018 | E67: FY 2019 | F67: FY 2020 | G67: FY 2021 | H67: FY 2022 | I67: FY 2023 | J67: FY 2024 Est | K67: FY 2025 Est | L67: FY 2026 Est | M67: FY 2027 Est | N67: FY 2027 Est
B68: 12 Months Ending | C68: 12/31/2017 | D68: 12/31/2018 | E68: 12/31/2019 | F68: 12/31/2020 | G68: 12/31/2021 | H68: 12/31/2022 | I68: 12/31/2023
B69: Total Assets
B70: + Cash, Cash Equivalents & STI | C70: 7029 | D70: 8242 | E70: 8597 | F70: 11932 | G70: 11365 | H70: 13417 | I70: 16251 | J70: =J138-SUM(J73,J76,J77,J83,J86,J89) -> 22065.58 | K70: =K138-SUM(K73,K76,K77,K83,K86,K89) -> 26279.131 | L70: =L138-SUM(L73,L76,L77,L83,L86,L89) -> 30781.826 | M70: =M138-SUM(M73,M76,M77,M83,M86,M89) -> 36439.98 | N70: =N138-SUM(N73,N76,N77,N83,N86,N89) -> 42555.392
B71: + Cash & Cash Equivalents | C71: 5710 | D71: 6551 | E71: 7261 | F71: 7981 | G71: 10332 | H71: 11251 | I71: 13775
B72: + ST Investments | C72: 1319 | D72: 1691 | E72: 1336 | F72: 3951 | G72: 1033 | H72: 2166 | I72: 2476
B73: + Accounts & Notes Receiv | C73: 6361 | D73: 7036 | E73: 7694 | F73: 6227 | G73: 7916 | H73: 8593 | I73: 8827 | J73: =J171*J$7 -> 9722.3463 | K73: =K171*K$7 -> 10492.014 | L73: =L171*L$7 -> 11324.798 | M73: =M171*M$7 -> 12211.619 | N73: =N171*N$7 -> 12731.57
B74: + Accounts Receivable, Net | C74: 6361 | D74: 7036 | E74: 7694 | F74: 6227 | G74: 7916 | H74: 8593 | I74: 8827 | J74: =J73 -> 9722.3463 | K74: =K73 -> 10492.014 | L74: =L73 -> 11324.798 | M74: =M73 -> 12211.619 | N74: =N73 -> 12731.57
B75: + Notes Receivable, Net | C75: 0 | D75: 0 | E75: 0 | F75: 0 | G75: 0 | H75: 0 | I75: 0 | J75: 0 | K75: 0 | L75: 0 | M75: 0 | N75: 1
B76: + Inventories | C76: 1056 | D76: 1173 | E76: 1434 | F76: 1428 | G76: 1591 | H76: 1785 | I76: 1878 | J76: =J174*J$7 -> 2160.5214 | K76: =K174*K$7 -> 2248.2887 | L76: =L174*L$7 -> 2343.0617 | M76: =M174*M$7 -> 2442.3238 | N76: =N174*N$7 -> 2546.3141
B77: + Other ST Assets | C77: 11831 | D77: 12170 | E77: 12503 | F77: 12452 | G77: 15050 | H77: 17902 | I77: 18816 | J77: =SUM(J78:J81) -> 19948.814 | K77: =SUM(K78:K81) -> 20759.199 | L77: =SUM(L78:L81) -> 21634.27 | M77: =SUM(M78:M81) -> 22550.79 | N77: =SUM(N78:N81) -> 23510.967
B78: + Derivative & Hedging Assets | C78: 261 | D78: 258 | E78: 210 | F78: 201 | G78: 291 | H78: 115 | I78: 94 | J78: =J176*J$7 -> 144.03476 | K78: =K176*K$7 -> 149.88591 | L78: =L176*L$7 -> 156.20411 | M78: =M176*M$7 -> 162.82159 | N78: =N176*N$7 -> 169.75427
B79: + Assets Held-for-Sale | C79: — | D79: — | E79: — | F79: — | G79: 569 | H79: 627 | I79: 702 | J79: =J177*J$7 -> 720.1738 | K79: =K177*K$7 -> 749.42957 | L79: =L177*L$7 -> 781.02056 | M79: =M177*M$7 -> 814.10793 | N79: =N177*N$7 -> 848.77136
B80: + Taxes Receivable | C80: 406 | D80: 280 | E80: 166 | F80: 266 | G80: 238 | H80: 259 | I80: 351 | J80: =J178*J$7 -> 360.0869 | K80: =K178*K$7 -> 374.71479 | L80: =L178*L$7 -> 390.51028 | M80: =M178*M$7 -> 407.05396 | N80: =N178*N$7 -> 424.38568
B81: + Misc ST Assets | C81: 11164 | D81: 11632 | E81: 12127 | F81: 11985 | G81: 13952 | H81: 16901 | I81: 17669 | J81: =J179*J$7 -> 18724.519 | K81: =K179*K$7 -> 19485.169 | L81: =L179*L$7 -> 20306.535 | M81: =M179*M$7 -> 21166.806 | N81: =N179*N$7 -> 22068.055
B82: Total Current Assets | C82: 26276 | D82: 28621 | E82: 30228 | F82: 32039 | G82: 35922 | H82: 41697 | I82: 45772 | J82: =J70+J73+J76+J77 -> 53897.262 | K82: =K70+K73+K76+K77 -> 59778.633 | L82: =L70+L73+L76+L77 -> 66083.956 | M82: =M70+M73+M76+M77 -> 73644.713 | N82: =N70+N73+N76+N77 -> 81344.243
B83: + Property, Plant & Equip, Net | C83: 4421 | D83: 5359 | E83: 10189 | F83: 9760 | G83: 10303 | H83: 10805 | I83: 13012 | J83: =J249 -> 12808.042 | K83: =K249 -> 12717.773 | L83: =L249 -> 12738.366 | M83: =M249 -> 12856.004 | N83: =N249 -> 13325.951
B84: + Property, Plant & Equip | C84: 13416 | D84: 14874 | E84: 20997 | F84: 21731 | G84: 23933 | H84: 25297 | I84: 28504 | J84: =J247 -> 31744.782 | K84: =K247 -> 35117.215 | L84: =L247 -> 38631.808 | M84: =M247 -> 42295.293 | N84: =N247 -> 46114.764
B85: - Accumulated Depreciation | C85: 8995 | D85: 9515 | E85: 10808 | F85: 11971 | G85: 13630 | H85: 14492 | I85: 15486 | J85: =J248 -> 18936.74 | K85: =K248 -> 22399.442 | L85: =L248 -> 25893.441 | M85: =M248 -> 29439.289 | N85: =N248 -> 32788.813
B86: + LT Investments & Receivables | C86: 1102 | D86: 1332 | E86: 1525 | F86: 2237 | G86: 2449 | H86: 2587 | I86: 2644 | J86: =SUM(J87:J88) -> 2880.6952 | K86: =SUM(K87:K88) -> 3185.0757 | L86: =SUM(L87:L88) -> 3319.3374 | M86: =SUM(M87:M88) -> 3459.9587 | N86: =SUM(N87:N88) -> 3607.2783
B87: + LT Investments | C87: 272 | D87: 273 | E87: 365 | F87: 1203 | G87: 1288 | H87: 1342 | I87: 1371 | J87: =J185*J$7 -> 1440.3476 | K87: =K185*K$7 -> 1686.2165 | L87: =L185*L$7 -> 1757.2963 | M87: =M185*M$7 -> 1831.7428 | N87: =N185*N$7 -> 1909.7355
B88: + LT Receivables | C88: 830 | D88: 1059 | E88: 1160 | F88: 1034 | G88: 1161 | H88: 1245 | I88: 1273 | J88: =J186*J$7 -> 1440.3476 | K88: =K186*K$7 -> 1498.8591 | L88: =L186*L$7 -> 1562.0411 | M88: =M186*M$7 -> 1628.2159 | N88: =N186*N$7 -> 1697.5427
B89: + Other LT Assets | C89: 38004 | D89: 40045 | E89: 49217 | F89: 47129 | G89: 52142 | H89: 56902 | I89: 57130 | J89: =SUM(J91:J96) -> 57130 | K89: =SUM(K91:K96) -> 57130 | L89: =SUM(L91:L96) -> 57130 | M89: =SUM(M91:M96) -> 57130 | N89: =SUM(N91:N96) -> 57130
B90: + Total Intangible Assets | C90: 35556 | D90: 37542 | E90: 45926 | F90: 44350 | G90: 49849 | H90: 54628 | I90: 54616 | J90: =I90 -> 54616 | K90: =J90 -> 54616 | L90: =K90 -> 54616 | M90: =L90 -> 54616 | N90: =M90 -> 54616
B91: + Goodwill | C91: 8600 | D91: 9792 | E91: 11647 | F91: 11619 | G91: 16099 | H91: 17360 | I91: 17578 | J91: =I91 -> 17578 | K91: =J91 -> 17578 | L91: =K91 -> 17578 | M91: =L91 -> 17578 | N91: =M91 -> 17578
B92: + Other Intangible Assets | C92: 26956 | D92: 27750 | E92: 34279 | F92: 32731 | G92: 33750 | H92: 37268 | I92: 37038 | J92: =I92 -> 37038 | K92: =J92 -> 37038 | L92: =K92 -> 37038 | M92: =L92 -> 37038 | N92: =M92 -> 37038
B93: + Deferred Tax Assets | C93: 255 | D93: 317 | E93: 370 | F93: 493 | G93: 767 | H93: 883 | I93: 1122 | J93: =I93 -> 1122 | K93: =J93 -> 1122 | L93: =K93 -> 1122 | M93: =L93 -> 1122 | N93: =M93 -> 1122
B94: + Derivative & Hedging Assets | C94: 621 | D94: 511 | E94: 1051 | F94: 1250 | G94: 575 | H94: 376 | I94: 125 | J94: =I94 -> 125 | K94: =J94 -> 125 | L94: =K94 -> 125 | M94: =L94 -> 125 | N94: =M94 -> 125
B95: + Investments in Affiliates | C95: 1054 | D95: 1674 | E95: 1870 | F95: 1035 | G95: 950 | H95: 1014 | I95: 1267 | J95: =I95 -> 1267 | K95: =J95 -> 1267 | L95: =K95 -> 1267 | M95: =L95 -> 1267 | N95: =M95 -> 1267
B96: + Misc LT Assets | C96: 518 | D96: 1 | E96: 0 | F96: 1 | G96: 1 | H96: 1 | I96: 0 | J96: =I96 -> 0 | K96: =J96 -> 0 | L96: =K96 -> 0 | M96: =L96 -> 0 | N96: =M96 -> 0
B97: Total Noncurrent Assets | C97: 43527 | D97: 46736 | E97: 60931 | F97: 59126 | G97: 64894 | H97: 70294 | I97: 72786 | J97: =SUM(J83,J86,J89) -> 72818.738 | K97: =SUM(K83,K86,K89) -> 73032.849 | L97: =SUM(L83,L86,L89) -> 73187.704 | M97: =SUM(M83,M86,M89) -> 73445.963 | N97: =SUM(N83,N86,N89) -> 74063.23
B98: Total Assets | C98: 69803 | D98: 75357 | E98: 91159 | F98: 91165 | G98: 100816 | H98: 111991 | I98: 118558 | J98: =SUM(J97,J82) -> 126716 | K98: =SUM(K97,K82) -> 132811.48 | L98: =SUM(L97,L82) -> 139271.66 | M98: =SUM(M97,M82) -> 147090.68 | N98: =SUM(N97,N82) -> 155407.47
B100: Liabilities & Shareholders' Equity
B101: + Payables & Accruals | C101: 20275 | D101: 21384 | E101: 23645 | F101: 23765 | G101: 29123 | H101: 34010 | I101: 36597 | J101: =SUM(J102:J104) -> 38061.185 | K101: =SUM(K102:K104) -> 39607.353 | L101: =SUM(L102:L104) -> 41276.937 | M101: =SUM(M102:M104) -> 43025.604 | N101: =SUM(N102:N104) -> 44857.566
B102: + Accounts Payable | C102: 8198 | D102: 8240 | E102: 8514 | F102: 8876 | G102: 12027 | H102: 13088 | I102: 13572 | J102: =J200*J$7 -> 14403.476 | K102: =K200*K$7 -> 14988.591 | L102: =L200*L$7 -> 15620.411 | M102: =M200*M$7 -> 16282.159 | N102: =N200*N$7 -> 16975.427
B103: + Accrued Taxes | C103: 225 | D103: 282 | E103: 292 | F103: 221 | G103: 360 | H103: 607 | I103: 594 | J103: =J201*J$7 -> 612.14773 | K103: =K201*K$7 -> 637.01513 | L103: =L201*L$7 -> 663.86748 | M103: =M201*M$7 -> 691.99174 | N103: =N201*N$7 -> 721.45565
B104: + Other Payables & Accruals | C104: 11852 | D104: 12862 | E104: 14839 | F104: 14668 | G104: 16736 | H104: 20315 | I104: 22431 | J104: =J202*J$7 -> 23045.562 | K104: =K202*K$7 -> 23981.746 | L104: =L202*L$7 -> 24992.658 | M104: =M202*M$7 -> 26051.454 | N104: =N202*N$7 -> 27160.683
B105: + ST Debt | C105: 4831 | D105: 4635 | E105: 4721 | F105: 4410 | G105: 6293 | H105: 6890 | I105: 5528 | J105: =SUM(J106:J109) -> 5977.4425 | K105: =SUM(K106:K109) -> 6220.2654 | L105: =SUM(L106:L109) -> 6482.4707 | M105: =SUM(M106:M109) -> 6757.0958 | N105: =SUM(N106:N109) -> 7045.8022
B106: + ST Borrowings | C106: 2191 | D106: 2577 | E106: 1792 | F106: 1950 | G106: 2240 | H106: 4107 | I106: 3000 | J106: =J204*J$7 -> 3240.7821 | K106: =K204*K$7 -> 3372.4331 | L106: =L204*L$7 -> 3514.5925 | M106: =M204*M$7 -> 3663.4857 | N106: =N204*N$7 -> 3819.4711
B107: + ST Lease Liabilities | C107: 33 | D107: 43 | E107: 504 | F107: 500 | G107: 524 | H107: 522 | I107: 572 | J107: =J205*J$7 -> 576.13904 | K107: =K205*K$7 -> 599.54366 | L107: =L205*L$7 -> 624.81645 | M107: =M205*M$7 -> 651.28634 | N107: =N205*N$7 -> 679.01708
B108: + ST Finance Leases | C108: 33 | D108: 43 | E108: — | F108: — | G108: — | H108: — | I108: — | J108: 0 | K108: 0 | L108: 0 | M108: 0 | N108: 1
B109: + Current Portion of LT Debt | C109: 2607 | D109: 2015 | E109: 2425 | F109: 1960 | G109: 3529 | H109: 2261 | I109: 1956 | J109: =J207*J$7 -> 2160.5214 | K109: =K207*K$7 -> 2248.2887 | L109: =L207*L$7 -> 2343.0617 | M109: =M207*M$7 -> 2442.3238 | N109: =N207*N$7 -> 2546.3141
B110: + Other ST Liabilities | C110: 4923 | D110: 5029 | E110: 5141 | F110: 5293 | G110: 6850 | H110: 7366 | I110: 8218 | J110: =SUM(J111:J113) -> 8281.9987 | K110: =SUM(K111:K113) -> 8618.4401 | L110: =SUM(L111:L113) -> 8981.7365 | M110: =SUM(M111:M113) -> 9362.2412 | N110: =SUM(N111:N113) -> 9760.8706
B111: + Deferred Revenue | C111: 0 | D111: 0 | E111: 0 | F111: 0 | G111: 0 | H111: 0 | I111: 0 | J111: =J209*J$7 -> 0 | K111: =K209*K$7 -> 0 | L111: =L209*L$7 -> 0 | M111: =M209*M$7 -> 0 | N111: =N209*N$7 -> 0
B112: + Derivatives & Hedging | C112: 114 | D112: 76 | E112: 399 | F112: 319 | G112: 513 | H112: 440 | I112: 476 | J112: =J210*J$7 -> 360.0869 | K112: =K210*K$7 -> 374.71479 | L112: =L210*L$7 -> 390.51028 | M112: =M210*M$7 -> 407.05396 | N112: =N210*N$7 -> 424.38568
B113: + Misc ST Liabilities | C113: 4809 | D113: 4953 | E113: 4742 | F113: 4974 | G113: 6337 | H113: 6926 | I113: 7742 | J113: =J211*J$7 -> 7921.9118 | K113: =K211*K$7 -> 8243.7253 | L113: =L211*L$7 -> 8591.2262 | M113: =M211*M$7 -> 8955.1872 | N113: =N211*N$7 -> 9336.4849
B114: Total Current Liabilities | C114: 30029 | D114: 31048 | E114: 33507 | F114: 33468 | G114: 42266 | H114: 48266 | I114: 50343 | J114: =SUM(J110,J105,J101) -> 52320.627 | K114: =SUM(K110,K105,K101) -> 54446.058 | L114: =SUM(L110,L105,L101) -> 56741.144 | M114: =SUM(M110,M105,M101) -> 59144.941 | N114: =SUM(N110,N105,N101) -> 61664.239
B115: + LT Debt | C115: 16642 | D115: 19611 | E115: 27733 | F115: 28091 | G115: 26543 | H115: 25210 | I115: 27508 | J115: =SUM(J116,J117) -> 30977.917 | K115: =SUM(K116,K117) -> 31583.061 | L115: =SUM(L116,L117) -> 32080.587 | M115: =SUM(M116,M117) -> 33537.507 | N115: =SUM(N116,N117) -> 35069.833
B116: + LT Borrowings | C116: 16545 | D116: 19488 | E116: 26375 | F116: 26684 | G116: 24969 | H116: 23630 | I116: 25833 | J116: =J158 -> 29249.5 | K116: =K158 -> 29784.43 | L116: =L158 -> 30206.138 | M116: =M158 -> 31583.648 | N116: =N158 -> 33032.782
B117: + LT Lease Liabilities | C117: 97 | D117: 123 | E117: 1358 | F117: 1407 | G117: 1574 | H117: 1580 | I117: 1675 | J117: =J215*J$7 -> 1728.4171 | K117: =K215*K$7 -> 1798.631 | L117: =L215*L$7 -> 1874.4494 | M117: =M215*M$7 -> 1953.859 | N117: =N215*N$7 -> 2037.0513
B118: + LT Finance Leases | C118: 97 | D118: 123 | E118: — | F118: — | G118: — | H118: — | I118: — | J118: 0 | K118: 0 | L118: 0 | M118: 0 | N118: 1
B119: + Other LT Liabilities | C119: 4749 | D119: 4880 | E119: 6877 | F119: 6433 | G119: 7235 | H119: 9106 | I119: 8666 | J119: =SUM(J120:J125) -> 8642.0856 | K119: =SUM(K120:K125) -> 8993.1548 | L119: =SUM(L120:L125) -> 9372.2468 | M119: =SUM(M120:M125) -> 9769.2952 | N119: =SUM(N120:N125) -> 10187.256
B120: + Accrued Liabilities | C120: 0 | D120: 0 | E120: 0 | F120: 0 | G120: 0 | H120: 0 | I120: 0 | J120: 0 | K120: 0 | L120: 0 | M120: 0 | N120: 1
B121: + Pension Liabilities | C121: 1481 | D121: 1519 | E121: 1911 | F121: 1535 | G121: 1459 | H121: 1149 | I121: 1176 | J121: =J219*J$7 -> 1224.2955 | K121: =K219*K$7 -> 1274.0303 | L121: =L219*L$7 -> 1327.735 | M121: =M219*M$7 -> 1383.9835 | N121: =N219*N$7 -> 1442.9113
...

Sheet Segment Rev+OPI build
W4: In Millions of EUR except Per Share | Y4: FY 2014 | Z4: FY 2015 | AA4: FY 2016 | AB4: FY 2017 | AC4: FY 2018 | AD4: FY 2019 | AE4: FY 2020 | AF4: FY 2021 | AG4: FY 2022 | AH4: FY 2023 | AI4: FY 2024 Est | AJ4: FY 2025 Est | AK4: FY 2026 Est | AL4: FY 2027 Est | AM4: FY 2028 Est
W5: 12 Months Ending
W6: Concessions
W7: Revenue | Y7: =SUM(Y8,Y10,Y14) -> 5823 | Z7: =SUM(Z8,Z10,Z14) -> 5803 | AA7: =SUM(AA8,AA10,AA14) -> 6297.98 | AB7: =SUM(AB8,AB10,AB14) -> 6944.6 | AC7: =SUM(AC8,AC10,AC14) -> 7255.58 | AD7: =SUM(AD8,AD10,AD14) -> 8544.58 | AE7: =SUM(AE8,AE10,AE14) -> 5837.8 | AF7: =SUM(AF8,AF10,AF14) -> 7047 | ... AM7: =SUM(AM8,AM10,AM14) -> 13710.743
W8: Road | Y8: 4743 | Z8: 4881 | AA8: 5111.49 | AB8: 5277.3 | AC8: 5356 | AD8: 5594.58 | AE8: 4612.8 | AF8: 5550 | AG8: 6003 | AH8: 6324 | AI8: =AH8*(1+AI9) -> 6513.72 | AJ8: =AI8*(1+AJ9) -> 6709.1316 | AK8: =AJ8*(1+AK9) -> 6910.4055 | AL8: =AK8*(1+AL9) -> 7117.7177 | AM8: =AL8*(1+AM9) -> 7331.2492
W9: %growth | Z9: =(Z8-Y8)/Y8 -> 0.029095509 | AA9: =(AA8-Z8)/Z8 -> 0.047221881 | AB9: =(AB8-AA8)/AA8 -> 0.032438682 | AC9: =(AC8-AB8)/AB8 -> 0.014912929 | AD9: =(AD8-AC8)/AC8 -> 0.044544436 | AE9: =(AE8-AD8)/AD8 -> -0.1754877 | AF9: =(AF8-AE8)/AE8 -> 0.20317378 | AG9: =(AG8-AF8)/AF8 -> 0.081621622 | AH9: =(AH8-AG8)/AG8 -> 0.053473263 | AI9: 0.03 | AJ9: 0.03 | AK9: 0.03 | AL9: 0.03 | AM9: 0.03
W10: Air | Y10: 717 | Z10: 820 | AA10: 1055.49 | AB10: 1409 | AC10: 1601.58 | AD10: 2631 | AE10: 990 | AF10: 1188 | AG10: 2679 | AH10: 3947 | AI10: =AH10*(1+AI11) -> 4223.29 | AJ10: =AI10*(1+AJ11) -> 4518.9203 | AK10: =AJ10*(1+AK11) -> 4835.2447 | AL10: =AK10*(1+AL11) -> 5173.7119 | AM10: =AL10*(1+AM11) -> 5535.8717
W11: %growth | Z11: =(Z10-Y10)/Y10 -> 0.14365411 | AA11: =(AA10-Z10)/Z10 -> 0.28718293 | AB11: =(AB10-AA10)/AA10 -> 0.33492501 | AC11: =(AC10-AB10)/AB10 -> 0.1366785 | AD11: =(AD10-AC10)/AC10 -> 0.64275278 | AE11: =(AE10-AD10)/AD10 -> -0.62371722 | AF11: =(AF10-AE10)/AE10 -> 0.2 | AG11: =(AG10-AF10)/AF10 -> 1.2550505 | AH11: =(AH10-AG10)/AG10 -> 0.47331094 | AI11: 0.07 | AJ11: 0.07 | AK11: 0.07 | AL11: 0.07 | AM11: 0.07
W12: Park
W13: %growth
W14: Other | Y14: 363 | Z14: 102 | AA14: 131 | AB14: 258.3 | AC14: 298 | AD14: 319 | AE14: 235 | AF14: 309 | AG14: 479 | AH14: 661 | AI14: =AH14*(1+AI15) -> 694.05 | AJ14: =AI14*(1+AJ15) -> 728.7525 | AK14: =AJ14*(1+AK15) -> 765.19013 | AL14: =AK14*(1+AL15) -> 803.44963 | AM14: =AL14*(1+AM15) -> 843.62211
W15: %growth | Z15: =(Z14-Y14)/Y14 -> -0.71900826 | AA15: =(AA14-Z14)/Z14 -> 0.28431373 | AB15: =(AB14-AA14)/AA14 -> 0.97175573 | AC15: =(AC14-AB14)/AB14 -> 0.15369725 | AD15: =(AD14-AC14)/AC14 -> 0.070469799 | AE15: =(AE14-AD14)/AD14 -> -0.26332288 | AF15: =(AF14-AE14)/AE14 -> 0.31489362 | AG15: =(AG14-AF14)/AF14 -> 0.55016181 | AH15: =(AH14-AG14)/AG14 -> 0.37995825 | AI15: 0.05 | AJ15: 0.05 | AK15: 0.05 | AL15: 0.05 | AM15: 0.05
W16: 0
W17: Operating margin | AA17: =AA18/AA7 -> 0.4688805 | AB17: =AB18/AB7 -> 0.46813351 | AC17: =AC18/AC7 -> 0.47260178 | AD17: =AD18/AD7 -> 0.46684565 | AE17: =AE18/AE7 -> 0.27167769 | AF17: =AF18/AF7 -> 0.38072939 | AG17: =AG18/AG7 -> 0.4554088 | AH17: =AH18/AH7 -> 0.49149286 | AI17: 0.48 | AJ17: 0.48 | AK17: 0.48 | AL17: 0.48 | AM17: 0.48
W18: Operating Income | AA18: 2953 | AB18: 3251 | AC18: 3429 | AD18: 3989 | AE18: 1586 | AF18: 2683 | AG18: 4172 | AH18: 5373 | AI18: =AI17*AI7 -> 5486.9088 | AJ18: =AJ17*AJ7 -> 5739.2661 | AK18: =AK17*AK7 -> 6005.2034 | AL18: =AL17*AL7 -> 6285.542 | AM18: =AM17*AM7 -> 6581.1567
W21: VINCI Immobilier & Holding Companies
W22: Revenue | Y22: 587 | Z22: 707 | AA22: 774 | AB22: 896 | AC22: 1104 | AD22: 1320 | AE22: 1191 | AF22: 2197 | AG22: 2113 | AH22: 2011 | AI22: =AH22*(1+AI23) -> 1005.5 | AJ22: =AI22*(1+AJ23) -> 1005.5 | AK22: =AJ22*(1+AK23) -> 1106.05 | AL22: =AK22*(1+AL23) -> 1216.655 | AM22: =AL22*(1+AM23) -> 1338.3205
P23: =AI7/AI54 -> 0.15872641 | Q23: =AH18/AH56 -> 0.64293407 | W23: % growth | Z23: =(Z22-Y22)/Y22 -> 0.2044293 | AA23: =(AA22-Z22)/Z22 -> 0.09476662 | AB23: =(AB22-AA22)/AA22 -> 0.15762274 | AC23: =(AC22-AB22)/AB22 -> 0.23214286 | AD23: =(AD22-AC22)/AC22 -> 0.19565217 | AE23: =(AE22-AD22)/AD22 -> -0.097727273 | AF23: =(AF22-AE22)/AE22 -> 0.84466835 | AG23: =(AG22-AF22)/AF22 -> -0.038233955 | AH23: =(AH22-AG22)/AG22 -> -0.048272598 | AI23: -0.5 | AJ23: 0 | AK23: 0.1 | AL23: 0.1 | AM23: 0.1
W24: Operating Margin | Y24: =Y25/Y22 -> 0.19080068 | Z24: =Z25/Z22 -> 0.12729844 | AA24: =AA25/AA22 -> 0.087855297 | AB24: =AB25/AB22 -> 0.13058036 | AC24: =AC25/AC22 -> 0.086050725 | AD24: =AD25/AD22 -> 0.06969697 | AE24: =AE25/AE22 -> 0.023509656 | AF24: =AF25/AF22 -> 0.038689122 | ... AH24: =AH25/AH22 -> -0.060666335 | AI24: 0.04 | AJ24: 0.04 | AK24: 0.04 | AL24: 0.04 | AM24: 0.04
W25: Operating Income | Y25: 112 | Z25: 90 | AA25: 68 | AB25: 117 | AC25: 95 | AD25: 92 | AE25: 28 | AF25: 85 | AG25: 0 | AH25: -122 | AI25: =AI24*AI22 -> 40.22 | AJ25: =AJ24*AJ22 -> 40.22 | AK25: =AK24*AK22 -> 44.242 | AL25: =AL24*AL22 -> 48.6662 | AM25: =AM24*AM22 -> 53.53282
W28: Cobra IS
W29: Revenue | AG29: 5520 | AH29: 6495 | AI29: =AH29*(1+AI30) -> 6884.7 | AJ29: =AI29*(1+AJ30) -> 7297.782 | AK29: =AJ29*(1+AK30) -> 7735.6489 | AL29: =AK29*(1+AL30) -> 8199.7879 | AM29: =AL29*(1+AM30) -> 8691.7751
W30: %growth | AH30: =(AH29-AG29)/AG29 -> 0.17663043 | AI30: 0.06 | AJ30: 0.06 | AK30: 0.06 | AL30: 0.06 | AM30: 0.06
W31: Operating Margin | AG31: =AG32/AG29 -> 0.074456522 | AH31: =AH32/AH29 -> 0.075442648 | AI31: 0.075 | AJ31: 0.075 | AK31: 0.075 | AL31: 0.075 | AM31: 0.075
W32: Operating Income | AG32: 411 | AH32: 490 | AI32: =AI31*AI29 -> 516.3525 | AJ32: =AJ31*AJ29 -> 547.33365 | AK32: =AK31*AK29 -> 580.17367 | AL32: =AL31*AL29 -> 614.98409 | AM32: =AM31*AM29 -> 651.88313
W35: VINCI Construction
W36: Revenue | Y36: 15419 | Z36: 14491 | AA36: 13681 | AB36: 13960 | AC36: 14231 | AD36: 14926 | AE36: 23149 | AF36: 26282 | AG36: 29252 | AH36: 31459 | AI36: =AH36*(1+AI37) -> 32402.77 | AJ36: =AI36*(1+AJ37) -> 33374.853 | AK36: =AJ36*(1+AK37) -> 34376.099 | AL36: =AK36*(1+AL37) -> 35407.382 | AM36: =AL36*(1+AM37) -> 36469.603
W37: % growth | Z37: =(Z36-Y36)/Y36 -> -0.060185485 | AA37: =(AA36-Z36)/Z36 -> -0.055896764 | AB37: =(AB36-AA36)/AA36 -> 0.020393246 | AC37: =(AC36-AB36)/AB36 -> 0.019412607 | AD37: =(AD36-AC36)/AC36 -> 0.048837046 | AE37: =(AE36-AD36)/AD36 -> 0.55091786 | AF37: =(AF36-AE36)/AE36 -> 0.13534062 | AG37: =(AG36-AF36)/AF36 -> 0.1130051 | AH37: =(AH36-AG36)/AG36 -> 0.075447833 | AI37: =0.03 -> 0.03 | AJ37: =0.03 -> 0.03 | AK37: =0.03 -> 0.03 | AL37: =0.03 -> 0.03 | AM37: =0.03 -> 0.03
W38: Operating Margin | Y38: =Y39/Y36 -> 0.020688761 | Z38: =Z39/Z36 -> 0.017045062 | AA38: =AA39/AA36 -> 0.024121044 | AB38: =AB39/AB36 -> 0.023137536 | AC38: =AC39/AC36 -> 0.028107652 | AD38: =AD39/AD36 -> 0.026530886 | AE38: =AE39/AE36 -> 0.020303253 | AF38: =AF39/AF36 -> 0.036831291 | ... AH38: =AH39/AH36 -> 0.040052131 | AI38: 0.04 | AJ38: 0.04 | AK38: 0.04 | AL38: 0.04 | AM38: 0.04
W39: Operating Income | Y39: 319 | Z39: 247 | AA39: 330 | AB39: 323 | AC39: 400 | AD39: 396 | AE39: 470 | AF39: 968 | AG39: 1100 | AH39: 1260 | AI39: =AI38*AI36 -> 1296.1108 | AJ39: =AJ38*AJ36 -> 1334.9941 | AK39: =AK38*AK36 -> 1375.0439 | AL39: =AL38*AL36 -> 1416.2953 | AM39: =AM38*AM36 -> 1458.7841
W44: Energy
W45: Revenue | Y45: 9309 | Z45: 10180 | AA45: 10200 | AB45: 10759 | AC45: 12603 | AD45: 13749 | AE45: 13661 | AF45: 15097 | AG45: 16748 | AH45: 19327 | AI45: =AH45*(1+AI46) -> 20293.35 | AJ45: =AI45*(1+AJ46) -> 21308.018 | AK45: =AJ45*(1+AK46) -> 22373.418 | AL45: =AK45*(1+AL46) -> 23492.089 | AM45: =AL45*(1+AM46) -> 24666.694
W46: % growth | Z46: =(Z45-Y45)/Y45 -> 0.093565367 | AA46: =(AA45-Z45)/Z45 -> 0.0019646365 | AB46: =(AB45-AA45)/AA45 -> 0.054803922 | AC46: =(AC45-AB45)/AB45 -> 0.17139139 | AD46: =(AD45-AC45)/AC45 -> 0.090930731 | AE46: =(AE45-AD45)/AD45 -> -0.0064004655 | AF46: =(AF45-AE45)/AE45 -> 0.10511676 | AG46: =(AG45-AF45)/AF45 -> 0.10935948 | AH46: =(AH45-AG45)/AG45 -> 0.15398854 | AI46: 0.05 | AJ46: 0.05 | AK46: 0.05 | AL46: 0.05 | AM46: 0.05
W47: Operating Margin | Y47: =Y48/Y45 -> 0.052314964 | Z47: =Z48/Z45 -> 0.051768173 | AA47: =AA48/AA45 -> 0.056960784 | AB47: =AB48/AB45 -> 0.050934102 | AC47: =AC48/AC45 -> 0.057684678 | AD47: =AD48/AD45 -> 0.060149829 | AE47: =AE48/AE45 -> 0.056584437 | AF47: =AF48/AF45 -> 0.065244751 | ... AH47: =AH48/AH45 -> 0.070160915 | AI47: 0.07 | AJ47: 0.07 | AK47: 0.07 | AL47: 0.07 | AM47: 0.07
W48: Operating Income | Y48: 487 | Z48: 527 | AA48: 581 | AB48: 548 | AC48: 727 | AD48: 827 | AE48: 773 | AF48: 985 | AG48: 1142 | AH48: 1356 | AI48: =AI47*AI45 -> 1420.5345 | AJ48: =AJ47*AJ45 -> 1491.5612 | AK48: =AK47*AK45 -> 1566.1393 | AL48: =AL47*AL45 -> 1644.4463 | AM48: =AM47*AM45 -> 1726.6686
W53: Group
W54: Revenue | Y54: =SUM(Y45,Y36,Y22,Y7,Y29) -> 31138 | Z54: =SUM(Z45,Z36,Z22,Z7,Z29) -> 31181 | AA54: =SUM(AA45,AA36,AA22,AA7,AA29) -> 30952.98 | AB54: =SUM(AB45,AB36,AB22,AB7,AB29) -> 32559.6 | AC54: =SUM(AC45,AC36,AC22,AC7,AC29) -> 35193.58 | AD54: =SUM(AD45,AD36,AD22,AD7,AD29) -> 38539.58 | AE54: =SUM(AE45,AE36,AE22,AE7,AE29) -> 43838.8 | AF54: =SUM(AF45,AF36,AF22,AF7,AF29) -> 50623 | ... AM54: =SUM(AM45,AM36,AM22,AM7,AM29) -> 84877.136
W55: % growth | AH55: =(AH54-AG54)/AG54 -> 0.11832341 | AI55: =(AI54-AH54)/AH54 -> 0.025537993 | AJ55: =(AJ54-AI54)/AI54 -> 0.040623208 | AK55: =(AK54-AJ54)/AJ54 -> 0.042153386 | AL55: =(AL54-AK54)/AK54 -> 0.04236427 | AM55: =(AM54-AL54)/AL54 -> 0.042578415
W56: Operating Income | AH56: =AH48+AH39+AH32+AH25+AH18 -> 8357 | AI56: =AI48+AI39+AI32+AI25+AI18 -> 8760.1266 | AJ56: =AJ48+AJ39+AJ32+AJ25+AJ18 -> 9153.3751 | AK56: =AK48+AK39+AK32+AK25+AK18 -> 9570.8023 | AL56: =AL48+AL39+AL32+AL25+AL18 -> 10009.934 | AM56: =AM48+AM39+AM32+AM25+AM18 -> 10472.025
W57: Operating Margin | AH57: =AH56/AH54 -> 0.1190049 | AI57: =AI56/AI54 -> 0.12163906 | AJ57: =AJ56/AJ54 -> 0.1221379 | AK57: =AK56/AK54 -> 0.12254226 | AL57: =AL56/AL54 -> 0.12295586 | AM57: =AM56/AM54 -> 0.12337864

Sheet OrderBook
F19: ="2014"&" Q1" -> 2014 Q1 | G19: ="2014"&" Q2" -> 2014 Q2 | H19: ="2014"&" Q3" -> 2014 Q3 | I19: ="2014"&" Q4" -> 2014 Q4 | J19: ="2015"&" Q1" -> 2015 Q1 | K19: ="2015"&" Q2" -> 2015 Q2 | L19: ="2015"&" Q3" -> 2015 Q3 | M19: ="2015"&" Q4" -> 2015 Q4 | N19: ="2016"&" Q1" -> 2016 Q1 | O19: ="2016"&" Q2" -> 2016 Q2 | P19: ="2016"&" Q3" -> 2016 Q3 | Q19: ="2016"&" Q4" -> 2016 Q4 | R19: ="2017"&" Q1" -> 2017 Q1 | S19: ="2017"&" Q2" -> 2017 Q2 | T19: ="2017"&" Q3" -> 2017 Q3 | U19: ="2017"&" Q4" -> 2017 Q4 | V19: ="2018"&" Q1" -> 2018 Q1 | W19: ="2018"&" Q2" -> 2018 Q2 | X19: ="2018"&" Q3" -> 2018 Q3 | Y19: ="2018"&" Q4" -> 2018 Q4 | Z19: ="2019"&" Q1" -> 2019 Q1 | AA19: ="2019"&" Q2" -> 2019 Q2 | AB19: ="2019"&" Q3" -> 2019 Q3 | AC19: ="2019"&" Q4" -> 2019 Q4 | AD19: ="2020"&" Q1" -> 2020 Q1 | AE19: ="2020"&" Q2" -> 2020 Q2 | AF19: ="2020"&" Q3" -> 2020 Q3 | AG19: ="2020"&" Q4" -> 2020 Q4 | AH19: ="2021"&" Q1" -> 2021 Q1 | AI19: ="2021"&" Q2" -> 2021 Q2 | AJ19: ="2021"&" Q3" -> 2021 Q3 | AK19: ="2021"&" Q4" -> 2021 Q4 | AL19: ="2022"&" Q1" -> 2022 Q1 | AM19: ="2022"&" Q2" -> 2022 Q2 | AN19: ="2022"&" Q3" -> 2022 Q3 | AO19: ="2022"&" Q4" -> 2022 Q4 | AP19: ="2023"&" Q1" -> 2023 Q1 | AQ19: ="2023"&" Q2" -> 2023 Q2 | AR19: ="2023"&" Q3" -> 2023 Q3 | AS19: ="2023"&" Q4" -> 2023 Q4 | AT19: 2024 Q1
E20: Vinci Energies Order Book | F20: 6800 | G20: 6600 | H20: 6400 | I20: 6300 | J20: 6600 | K20: 6800 | L20: 6500 | M20: 6100 | N20: 6600 | O20: 6400 | P20: 6200 | Q20: 5900 | R20: 6900 | S20: 7000 | T20: 7100 | U20: 6700 | V20: 8700 | W20: 8700 | X20: 8600 | Y20: 8400 | Z20: 9300 | AA20: 9400 | AB20: 9500 | AC20: 9100 | AD20: 10200 | AE20: 10200 | AF20: 10200 | AG20: 9900 | AH20: 10900 | AI20: 11200 | AJ20: 11400 | AK20: 11000 | AL20: 12200 | AM20: 12700 | AN20: 12600 | AO20: 12400 | AP20: 14500 | AQ20: 14700 | AR20: 14700 | AS20: 14300 | AT20: 16000
E21: Cobra IS Order Book | AL21: 8400 | AM21: 9300 | AN21: 11200 | AO21: 11100 | AP21: 11500 | AQ21: 13300 | AR21: 14900 | AS21: 14400 | AT21: 16700
E22: Vinci Construction Order Book | F22: 23900 | G22: 22900 | H22: 22300 | I22: 21600 | J22: 22500 | K22: 21900 | L22: 22000 | M22: 21700 | N22: 17000 | O22: 22800 | P22: 21700 | Q22: 21500 | R22: 23300 | S22: 23700 | T22: 23500 | U22: 22600 | V22: 24000 | W22: 24000 | X22: 24200 | Y22: 24700 | Z22: 25600 | AA22: 26800 | AB22: 27000 | AC22: 27400 | AD22: 27600 | AE22: 32700 | AF22: 32600 | AG22: 32500 | AH22: 35000 | AI22: 34800 | AJ22: 34000 | AK22: 33400 | AL22: 34300 | AM22: 34300 | AN22: 33600 | AO22: 33800 | AP22: 34300 | AQ22: 33600 | AR22: 33600 | AS22: 32700 | AT22: 33900
F30: ="2014"&" Q1" -> 2014 Q1 | G30: ="2014"&" Q2" -> 2014 Q2 | H30: ="2014"&" Q3" -> 2014 Q3 | I30: ="2014"&" Q4" -> 2014 Q4 | J30: ="2015"&" Q1" -> 2015 Q1 | K30: ="2015"&" Q2" -> 2015 Q2 | L30: ="2015"&" Q3" -> 2015 Q3 | M30: ="2015"&" Q4" -> 2015 Q4 | N30: ="2016"&" Q1" -> 2016 Q1 | O30: ="2016"&" Q2" -> 2016 Q2 | P30: ="2016"&" Q3" -> 2016 Q3 | Q30: ="2016"&" Q4" -> 2016 Q4 | R30: ="2017"&" Q1" -> 2017 Q1 | S30: ="2017"&" Q2" -> 2017 Q2 | T30: ="2017"&" Q3" -> 2017 Q3 | U30: ="2017"&" Q4" -> 2017 Q4 | V30: ="2018"&" Q1" -> 2018 Q1 | W30: ="2018"&" Q2" -> 2018 Q2 | X30: ="2018"&" Q3" -> 2018 Q3 | Y30: ="2018"&" Q4" -> 2018 Q4 | Z30: ="2019"&" Q1" -> 2019 Q1 | AA30: ="2019"&" Q2" -> 2019 Q2 | AB30: ="2019"&" Q3" -> 2019 Q3 | AC30: ="2019"&" Q4" -> 2019 Q4 | AD30: ="2020"&" Q1" -> 2020 Q1 | AE30: ="2020"&" Q2" -> 2020 Q2 | AF30: ="2020"&" Q3" -> 2020 Q3 | AG30: ="2020"&" Q4" -> 2020 Q4 | AH30: ="2021"&" Q1" -> 2021 Q1 | AI30: ="2021"&" Q2" -> 2021 Q2 | AJ30: ="2021"&" Q3" -> 2021 Q3 | AK30: ="2021"&" Q4" -> 2021 Q4 | AL30: ="2022"&" Q1" -> 2022 Q1 | AM30: ="2022"&" Q2" -> 2022 Q2 | AN30: ="2022"&" Q3" -> 2022 Q3 | AO30: ="2022"&" Q4" -> 2022 Q4 | AP30: ="2023"&" Q1" -> 2023 Q1 | AQ30: ="2023"&" Q2" -> 2023 Q2 | AR30: ="2023"&" Q3" -> 2023 Q3 | AS30: ="2023"&" Q4" -> 2023 Q4 | AT30: 2024 Q1
E31: Energies YoY Change | J31: =(J20-F20)/F20 -> -0.029411765 | K31: =(K20-G20)/G20 -> 0.03030303 | L31: =(L20-H20)/H20 -> 0.015625 | M31: =(M20-I20)/I20 -> -0.031746032 | N31: =(N20-J20)/J20 -> 0 | O31: =(O20-K20)/K20 -> -0.058823529 | P31: =(P20-L20)/L20 -> -0.046153846 | Q31: =(Q20-M20)/M20 -> -0.032786885 | ... AT31: =(AT20-AP20)/AP20 -> 0.10344828
E32: Cobra IS YoY Change | AP32: =(AP21-AL21)/AL21 -> 0.36904762 | AQ32: =(AQ21-AM21)/AM21 -> 0.43010753 | AR32: =(AR21-AN21)/AN21 -> 0.33035714 | AS32: =(AS21-AO21)/AO21 -> 0.2972973 | AT32: =(AT21-AP21)/AP21 -> 0.45217391
E33: Construction YoY Change | J33: =(J22-F22)/F22 -> -0.058577406 | K33: =(K22-G22)/G22 -> -0.043668122 | L33: =(L22-H22)/H22 -> -0.013452915 | M33: =(M22-I22)/I22 -> 0.0046296296 | N33: =(N22-J22)/J22 -> -0.24444444 | O33: =(O22-K22)/K22 -> 0.04109589 | P33: =(P22-L22)/L22 -> -0.013636364 | Q33: =(Q22-M22)/M22 -> -0.0092165899 | ... AT33: =(AT22-AP22)/AP22 -> -0.011661808
F35: ="2014"&" Q1" -> 2014 Q1 | G35: ="2014"&" Q2" -> 2014 Q2 | H35: ="2014"&" Q3" -> 2014 Q3 | I35: ="2014"&" Q4" -> 2014 Q4 | J35: ="2015"&" Q1" -> 2015 Q1 | K35: ="2015"&" Q2" -> 2015 Q2 | L35: ="2015"&" Q3" -> 2015 Q3 | M35: ="2015"&" Q4" -> 2015 Q4 | N35: ="2016"&" Q1" -> 2016 Q1 | O35: ="2016"&" Q2" -> 2016 Q2 | P35: ="2016"&" Q3" -> 2016 Q3 | Q35: ="2016"&" Q4" -> 2016 Q4 | R35: ="2017"&" Q1" -> 2017 Q1 | S35: ="2017"&" Q2" -> 2017 Q2 | T35: ="2017"&" Q3" -> 2017 Q3 | U35: ="2017"&" Q4" -> 2017 Q4 | V35: ="2018"&" Q1" -> 2018 Q1 | W35: ="2018"&" Q2" -> 2018 Q2 | X35: ="2018"&" Q3" -> 2018 Q3 | Y35: ="2018"&" Q4" -> 2018 Q4 | Z35: ="2019"&" Q1" -> 2019 Q1 | AA35: ="2019"&" Q2" -> 2019 Q2 | AB35: ="2019"&" Q3" -> 2019 Q3 | AC35: ="2019"&" Q4" -> 2019 Q4 | AD35: ="2020"&" Q1" -> 2020 Q1 | AE35: ="2020"&" Q2" -> 2020 Q2 | AF35: ="2020"&" Q3" -> 2020 Q3 | AG35: ="2020"&" Q4" -> 2020 Q4 | AH35: ="2021"&" Q1" -> 2021 Q1 | AI35: ="2021"&" Q2" -> 2021 Q2 | AJ35: ="2021"&" Q3" -> 2021 Q3 | AK35: ="2021"&" Q4" -> 2021 Q4 | AL35: ="2022"&" Q1" -> 2022 Q1 | AM35: ="2022"&" Q2" -> 2022 Q2 | AN35: ="2022"&" Q3" -> 2022 Q3 | AO35: ="2022"&" Q4" -> 2022 Q4 | AP35: ="2023"&" Q1" -> 2023 Q1 | AQ35: ="2023"&" Q2" -> 2023 Q2 | AR35: ="2023"&" Q3" -> 2023 Q3 | AS35: ="2023"&" Q4" -> 2023 Q4 | AT35: 2024 Q1
E36: Energies QoQ Change | G36: =(G20-F20)/F20 -> -0.029411765 | H36: =(H20-G20)/G20 -> -0.03030303 | I36: =(I20-H20)/H20 -> -0.015625 | J36: =(J20-I20)/I20 -> 0.047619048 | K36: =(K20-J20)/J20 -> 0.03030303 | L36: =(L20-K20)/K20 -> -0.044117647 | M36: =(M20-L20)/L20 -> -0.061538462 | N36: =(N20-M20)/M20 -> 0.081967213 | ... AT36: =(AT20-AS20)/AS20 -> 0.11888112
E37: Cobra IS QoQ Change | AM37: =(AM21-AL21)/AL21 -> 0.10714286 | AN37: =(AN21-AM21)/AM21 -> 0.20430108 | AO37: =(AO21-AN21)/AN21 -> -0.0089285714 | AP37: =(AP21-AO21)/AO21 -> 0.036036036 | AQ37: =(AQ21-AP21)/AP21 -> 0.15652174 | AR37: =(AR21-AQ21)/AQ21 -> 0.12030075 | AS37: =(AS21-AR21)/AR21 -> -0.033557047 | AT37: =(AT21-AS21)/AS21 -> 0.15972222
E38: Construction QoQ Change | G38: =(G22-F22)/F22 -> -0.041841004 | H38: =(H22-G22)/G22 -> -0.026200873 | I38: =(I22-H22)/H22 -> -0.031390135 | J38: =(J22-I22)/I22 -> 0.041666667 | K38: =(K22-J22)/J22 -> -0.026666667 | L38: =(L22-K22)/K22 -> 0.00456621 | M38: =(M22-L22)/L22 -> -0.013636364 | N38: =(N22-M22)/M22 -> -0.21658986 | ... AT38: =(AT22-AS22)/AS22 -> 0.036697248

Sheet SOTP
A2: Business Line | B2: 2025 EBIT | C2: Multiple/Method | D2: Value | E2: % SOTP
A3: Vinci Construction | B3: ='Segment Rev+OPI build'!AJ39 -> 1334.9941 | C3: 6 | D3: =(B3*C3) -> 8009.9647 | E3: =D3/$B$25 -> 0.086465727
A4: Vinci Energies | B4: ='Segment Rev+OPI build'!AJ48 -> 1491.5612 | C4: 11 | D4: =(B4*C4) -> 16407.173 | E4: =D4/$B$25 -> 0.17711166
A5: Cobra IS - Contracting | B5: ='Segment Rev+OPI build'!AJ32 -> 547.33365 | C5: 11 | D5: =(B5*C5) -> 6020.6701 | E5: =D5/$B$25 -> 0.06499175
A6: Contracting | B6: =SUM(B3:B5) -> 3373.889 | D6: =SUM(D3:D5) -> 30437.808 | E6: =D6/$B$25 -> 0.32856914
B8: BV
A9: Immobilier | B9: 113 | C9: 1 | D9: =(B9*C9) -> 113 | E9: =D9/$B$25 -> 0.001219809
A11: Concessions
A12: Cofiroute | C12: DCF | D12: =B79 -> 6201.6781 | E12: =D12/$B$25 -> 0.066945688
A13: ASF | C13: DCF | D13: =B92 -> 18460.278 | E13: =D13/$B$25 -> 0.19927446
A14: ARCOUR | C14: DCF | D14: =B105 -> 996.15472 | E14: =D14/$B$25 -> 0.010753261
A15: Gatwick | C15: DCF | D15: =B120 -> 7743.8815 | E15: =D15/$B$25 -> 0.08359342
A16: ANA | C16: DCF | D16: =B135 -> 12576.652 | E16: =D16/$B$25 -> 0.13576207
A17: ADP | C17: MKT VAL | D17: 910 | E17: =D17/$B$25 -> 0.0098232407
A18: OMA | C18: MKT VAL | D18: 962 | E18: =D18/$B$25 -> 0.010384569
A19: Lyon Airport | C19: TRANS VAL | D19: 535 | E19: =D19/$B$25 -> 0.005775202
A20: Edinburgh Airport | C20: TRANS VAL | D20: 4233 | E20: =D20/$B$25 -> 0.045694262
A21: Northwest Parkway (Denver) | C21: TRANS VAL | D21: 1126 | E21: =D21/$B$25 -> 0.012154911
A22: Other concessions | B22: 609 | C22: 12 | D22: =B22*C22 -> 7308 | E22: =D22/$B$25 -> 0.078888179
A23: Polo Carmópolis | C23: TRANS VAL | D23: 1034 | E23: =D23/$B$25 -> 0.011161792
A25: EV | B25: =SUM(D6:D23) -> 92637.453
A26: Net Debt | B26: -15391
A27: Minority Interest | B27: -5200
A28: Equity Value | B28: =SUM(B25:B27) -> 72046.453
A29: Per Share | B29: =B28/575 -> 125.29818
B69: 2024 | C69: =B69+1 -> 2025 | D69: =C69+1 -> 2026 | E69: =D69+1 -> 2027 | F69: =E69+1 -> 2028 | G69: =F69+1 -> 2029 | H69: =G69+1 -> 2030 | I69: =H69+1 -> 2031 | J69: =I69+1 -> 2032 | ... L69: =K69+1 -> 2034
A70: Cofiroute
A71: Toll Revenue | B71: 1622 | C71: =(1+C72)*B71 -> 1656.062 | D71: =(1+D72)*C71 -> 1690.8393 | E71: =(1+E72)*D71 -> 1726.3469 | F71: =(1+F72)*E71 -> 1762.6002 | G71: =(1+G72)*F71 -> 1799.6148 | H71: =(1+H72)*G71 -> 1837.4067 | I71: =(1+I72)*H71 -> 1875.9923 | J71: =(1+J72)*I71 -> 1915.3881 | ... L71: =(1+L72)*K71 -> 1996.6791
A72: Growth % | C72: 0.021 | D72: 0.021 | E72: 0.021 | F72: 0.021 | G72: 0.021 | H72: 0.021 | I72: 0.021 | J72: 0.021 | K72: 0.021 | L72: 0.021
A73: EBITDA Margin | B73: 0.7 | C73: 0.7 | D73: 0.7 | E73: 0.7 | F73: 0.7 | G73: 0.7 | H73: 0.7 | I73: 0.7 | J73: 0.7 | K73: 0.7 | L73: 0.7
A74: EBITDA | B74: =B73*B71 -> 1135.4 | C74: =C73*C71 -> 1159.2434 | D74: =D73*D71 -> 1183.5875 | E74: =E73*E71 -> 1208.4428 | F74: =F73*F71 -> 1233.8201 | G74: =G73*G71 -> 1259.7304 | H74: =H73*H71 -> 1286.1847 | I74: =I73*I71 -> 1313.1946 | ... L74: =L73*L71 -> 1397.6754 | N74: WACC | O74: Tax Rate
A75: Capex % of Tolls | B75: =0.03 -> 0.03 | C75: =0.03 -> 0.03 | D75: =0.03 -> 0.03 | E75: =0.03 -> 0.03 | F75: =0.03 -> 0.03 | G75: =0.03 -> 0.03 | H75: =0.03 -> 0.03 | I75: =0.03 -> 0.03 | ... L75: =0.03 -> 0.03
A76: Capex | B76: =-B75*B71 -> -48.66 | C76: =-C75*C71 -> -49.68186 | D76: =-D75*D71 -> -50.725179 | E76: =-E75*E71 -> -51.790408 | F76: =-F75*F71 -> -52.878006 | G76: =-G75*G71 -> -53.988445 | H76: =-H75*H71 -> -55.122202 | I76: =-I75*I71 -> -56.279768 | ... L76: =-L75*L71 -> -59.900373 | N76: 0.069 | O76: =0.26 -> 0.26
A77: Tax | B77: =-(B74)*$O$76 -> -295.204 | C77: =-(C74)*$O$76 -> -301.40328 | D77: =-(D74)*$O$76 -> -307.73275 | E77: =-(E74)*$O$76 -> -314.19514 | F77: =-(F74)*$O$76 -> -320.79324 | G77: =-(G74)*$O$76 -> -327.5299 | H77: =-(H74)*$O$76 -> -334.40802 | I77: =-(I74)*$O$76 -> -341.43059 | ... L77: =-(L74)*$O$76 -> -363.3956
A78: CF | B78: =SUM(B74,B76,B77) -> 791.536 | C78: =SUM(C74,C76,C77) -> 808.15826 | D78: =SUM(D74,D76,D77) -> 825.12958 | E78: =SUM(E74,E76,E77) -> 842.4573 | F78: =SUM(F74,F76,F77) -> 860.1489 | G78: =SUM(G74,G76,G77) -> 878.21203 | H78: =SUM(H74,H76,H77) -> 896.65448 | I78: =SUM(I74,I76,I77) -> 915.48423 | ... L78: =SUM(L74,L76,L77) -> 974.3794
A79: NPV | B79: =NPV(N76,C78:L78) -> 6201.6781
A83: ASF | B83: =B69 -> 2024 | C83: =C69 -> 2025 | D83: =D69 -> 2026 | E83: =E69 -> 2027 | F83: =F69 -> 2028 | G83: =G69 -> 2029 | H83: =H69 -> 2030 | I83: =I69 -> 2031 | ... L83: =L69 -> 2034 | M83: =2035 -> 2035 | N83: 2036 | P83: WACC | Q83: Tax Rate
A84: Toll Revenues | B84: 4708 | C84: =(1+C85)*B84 -> 4802.16 | D84: =(1+D85)*C84 -> 4898.2032 | E84: =(1+E85)*D84 -> 4996.1673 | F84: =(1+F85)*E84 -> 5096.0906 | G84: =(1+G85)*F84 -> 5198.0124 | H84: =(1+H85)*G84 -> 5301.9727 | I84: =(1+I85)*H84 -> 5408.0121 | J84: =(1+J85)*I84 -> 4867.2109 | ... N84: =(1+N85)*M84 -> 2582.5616 | Q84: 0.26
A85: Growth % | C85: 0.02 | D85: 0.02 | E85: 0.02 | F85: 0.02 | G85: 0.02 | H85: 0.02 | I85: 0.02 | J85: -0.1 | K85: 0.02 | L85: 0.02 | M85: 0.02 | N85: -0.5
A86: EBITDA Margin | B86: 0.7 | C86: 0.7 | D86: 0.7 | E86: 0.7 | F86: 0.7 | G86: 0.7 | H86: 0.7 | I86: 0.7 | J86: 0.7 | K86: 0.7 | L86: 0.7 | M86: 0.7 | N86: 0.7
A87: EBITDA | B87: =B86*B84 -> 3295.6 | C87: =C86*C84 -> 3361.512 | D87: =D86*D84 -> 3428.7422 | E87: =E86*E84 -> 3497.3171 | F87: =F86*F84 -> 3567.2634 | G87: =G86*G84 -> 3638.6087 | H87: =H86*H84 -> 3711.3809 | I87: =I86*I84 -> 3785.6085 | ... N87: =N86*N84 -> 1807.7931 | P87: 0.069
A88: Capex % of tolls | B88: 0.1 | C88: 0.1 | D88: 0.1 | E88: 0.04 | F88: 0.04 | G88: 0.03 | H88: 0.03 | I88: 0.03 | J88: 0.03 | K88: 0.03 | L88: 0.03 | M88: 0.03 | N88: 0.03
A89: Capex | B89: =-B88*B84 -> -470.8 | C89: =-C88*C84 -> -480.216 | D89: =-D88*D84 -> -489.82032 | E89: =-E88*E84 -> -199.84669 | F89: =-F88*F84 -> -203.84362 | G89: =-G88*G84 -> -155.94037 | H89: =-H88*H84 -> -159.05918 | I89: =-I88*I84 -> -162.24036 | ... N89: =-N88*N84 -> -77.476847
A90: Tax | B90: =SUM(B87)*-$Q$84 -> -856.856 | C90: =SUM(C87)*-$Q$84 -> -873.99312 | D90: =SUM(D87)*-$Q$84 -> -891.47298 | E90: =SUM(E87)*-$Q$84 -> -909.30244 | F90: =SUM(F87)*-$Q$84 -> -927.48849 | G90: =SUM(G87)*-$Q$84 -> -946.03826 | H90: =SUM(H87)*-$Q$84 -> -964.95903 | I90: =SUM(I87)*-$Q$84 -> -984.25821 | ... N90: =SUM(N87)*-$Q$84 -> -470.02621
A91: Operating CF | B91: =SUM(B87,B89:B90) -> 1967.944 | C91: =SUM(C87,C89:C90) -> 2007.3029 | D91: =SUM(D87,D89:D90) -> 2047.4489 | E91: =SUM(E87,E89:E90) -> 2388.168 | F91: =SUM(F87,F89:F90) -> 2435.9313 | G91: =SUM(G87,G89:G90) -> 2536.6301 | H91: =SUM(H87,H89:H90) -> 2587.3627 | I91: =SUM(I87,I89:I90) -> 2639.1099 | ... N91: =SUM(N87,N89:N90) -> 1260.2901
A92: NPV | B92: =NPV(P87,C91:N91) -> 18460.278 | P92: WACC | Q92: Tax
P93: 0.069 | Q93: 0.34
A96: ARCOUR | B96: 2024 | C96: 2025 | D96: 2026 | E96: 2027 | F96: 2028 | G96: 2029 | H96: 2030 | I96: 2031 | J96: 2032 | K96: 2033 | L96: 2034 | M96: 2035 | N96: 2036 | O96: =N96+1 -> 2037 | P96: =O96+1 -> 2038 | Q96: =P96+1 -> 2039 | R96: =Q96+1 -> 2040 | S96: =R96+1 -> 2041 | T96: =S96+1 -> 2042 | U96: =T96+1 -> 2043 | V96: =U96+1 -> 2044 | ... AV96: =AU96+1 -> 2070
A97: Toll Revenues | B97: 91 | C97: =(1+C98)*B97 -> 97.37 | D97: =(1+D98)*C97 -> 104.1859 | E97: =(1+E98)*D97 -> 111.47891 | F97: =(1+F98)*E97 -> 119.28244 | G97: =(1+G98)*F97 -> 122.2645 | H97: =(1+H98)*G97 -> 125.32111 | I97: =(1+I98)*H97 -> 128.45414 | J97: =(1+J98)*I97 -> 131.66549 | ... AV97: =(1+AV98)*AU97 -> 336.49518
A98: Growth % | C98: 0.07 | D98: 0.07 | E98: 0.07 | F98: 0.07 | G98: 0.025 | H98: 0.025 | I98: 0.025 | J98: 0.025 | K98: 0.025 | L98: 0.025 | M98: 0.025 | N98: 0.025 | O98: 0.025 | P98: 0.025 | Q98: 0.025 | R98: 0.025 | S98: 0.025 | T98: 0.025 | U98: 0.025 | V98: 0.025 | W98: 0.025 | X98: 0.025 | Y98: 0.025 | Z98: 0.025 | AA98: 0.025 | AB98: 0.025 | AC98: 0.025 | AD98: 0.025 | AE98: 0.025 | AF98: 0.025 | AG98: 0.025 | AH98: 0.025 | AI98: 0.025 | AJ98: 0.025 | AK98: 0.025 | AL98: 0.025 | AM98: 0.025 | AN98: 0.025 | AO98: 0.025 | AP98: 0.025 | AQ98: 0.025 | AR98: 0.025 | AS98: 0.025 | AT98: 0.025 | AU98: 0.025 | AV98: 0.025
A99: EBITDA Margin | B99: 0.8 | C99: 0.8 | D99: 0.8 | E99: 0.8 | F99: 0.8 | G99: 0.8 | H99: 0.8 | I99: 0.8 | J99: 0.8 | K99: 0.8 | L99: 0.8 | M99: 0.8 | N99: 0.8 | O99: 0.8 | P99: 0.8 | Q99: 0.8 | R99: 0.8 | S99: 0.8 | T99: 0.8 | U99: 0.8 | V99: 0.8 | W99: 0.8 | X99: 0.8 | Y99: 0.8 | Z99: 0.8 | AA99: 0.8 | AB99: 0.8 | AC99: 0.8 | AD99: 0.8 | AE99: 0.8 | AF99: 0.8 | AG99: 0.8 | AH99: 0.8 | AI99: 0.8 | AJ99: 0.8 | AK99: 0.8 | AL99: 0.8 | AM99: 0.8 | AN99: 0.8 | AO99: 0.8 | AP99: 0.8 | AQ99: 0.8 | AR99: 0.8 | AS99: 0.8 | AT99: 0.8 | AU99: 0.8 | AV99: 0.8
A100: EBITDA | B100: =B99*B97 -> 72.8 | C100: =C99*C97 -> 77.896 | D100: =D99*D97 -> 83.34872 | E100: =E99*E97 -> 89.18313 | F100: =F99*F97 -> 95.42595 | G100: =G99*G97 -> 97.811598 | H100: =H99*H97 -> 100.25689 | I100: =I99*I97 -> 102.76331 | ... AV100: =AV99*AV97 -> 269.19615
A101: Capex % of tolls | B101: 0.06 | C101: 0.06 | D101: 0.06 | E101: 0.06 | F101: 0.06 | G101: 0.06 | H101: 0.06 | I101: 0.06 | J101: 0.06 | K101: 0.06 | L101: 0.06 | M101: 0.06 | N101: 0.06 | O101: 0.06 | P101: 0.06 | Q101: 0.06 | R101: 0.06 | S101: 0.06 | T101: 0.06 | U101: 0.06 | V101: 0.06 | W101: 0.06 | X101: 0.06 | Y101: 0.06 | Z101: 0.06 | AA101: 0.06 | AB101: 0.06 | AC101: 0.06 | AD101: 0.06 | AE101: 0.06 | AF101: 0.06 | AG101: 0.06 | AH101: 0.06 | AI101: 0.06 | AJ101: 0.06 | AK101: 0.06 | AL101: 0.06 | AM101: 0.06 | AN101: 0.06 | AO101: 0.06 | AP101: 0.06 | AQ101: 0.06 | AR101: 0.06 | AS101: 0.06 | AT101: 0.06 | AU101: 0.06 | AV101: 0.06
A102: Capex | B102: =-B101*B97 -> -5.46 | C102: =-C101*C97 -> -5.8422 | D102: =-D101*D97 -> -6.251154 | E102: =-E101*E97 -> -6.6887348 | F102: =-F101*F97 -> -7.1569462 | G102: =-G101*G97 -> -7.3358699 | H102: =-H101*H97 -> -7.5192666 | I102: =-I101*I97 -> -7.7072483 | ... AV102: =-AV101*AV97 -> -20.189711
A103: Tax | B103: =-SUM(B100)*$Q$93 -> -24.752 | C103: =-SUM(C100)*$Q$93 -> -26.48464 | D103: =-SUM(D100)*$Q$93 -> -28.338565 | E103: =-SUM(E100)*$Q$93 -> -30.322264 | F103: =-SUM(F100)*$Q$93 -> -32.444823 | G103: =-SUM(G100)*$Q$93 -> -33.255943 | H103: =-SUM(H100)*$Q$93 -> -34.087342 | I103: =-SUM(I100)*$Q$93 -> -34.939526 | ... AV103: =-SUM(AV100)*$Q$93 -> -91.526689
A104: Operating CF | B104: =SUM(B103,B102,B100) -> 42.588 | C104: =SUM(C103,C102,C100) -> 45.56916 | D104: =SUM(D103,D102,D100) -> 48.759001 | E104: =SUM(E103,E102,E100) -> 52.172131 | F104: =SUM(F103,F102,F100) -> 55.82418 | G104: =SUM(G103,G102,G100) -> 57.219785 | H104: =SUM(H103,H102,H100) -> 58.65028 | I104: =SUM(I103,I102,I100) -> 60.116537 | ... AV104: =SUM(AV103,AV102,AV100) -> 157.47974
A105: NPV | B105: =NPV(P93,C104:AV104) -> 996.15472
J108: WACC | K108: Tax | L108: Termanil growth
J109: 0.071 | K109: 0.19 | L109: 0.025
A110: Gatwick | B110: 2024 | C110: 2025 | D110: 2026 | E110: 2027 | F110: 2028 | G110: 2029 | H110: 2030 | I110: Terminal
A111: Revenues | B111: 929 | C111: =(1+C112)*B111 -> 966.16 | D111: =(1+D112)*C111 -> 1004.8064 | E111: =(1+E112)*D111 -> 1044.9987 | F111: =(1+F112)*E111 -> 1086.7986 | G111: =(1+G112)*F111 -> 1130.2705 | H111: =(1+H112)*G111 -> 1175.4814
A112: Growth % | C112: 0.04 | D112: 0.04 | E112: 0.04 | F112: 0.04 | G112: 0.04 | H112: 0.04
A113: EBITDA Margin | B113: 0.58 | C113: 0.58 | D113: 0.58 | E113: 0.58 | F113: 0.58 | G113: 0.58 | H113: 0.58
A114: EBITDA | B114: =B113*B111 -> 538.82 | C114: =C113*C111 -> 560.3728 | D114: =D113*D111 -> 582.78771 | E114: =E113*E111 -> 606.09922 | F114: =F113*F111 -> 630.34319 | G114: =G113*G111 -> 655.55692 | H114: =H113*H111 -> 681.77919
A115: Capex % of revenue | B115: 0.15 | C115: 0.15 | D115: 0.15 | E115: 0.15 | F115: 0.15 | G115: 0.15 | H115: 0.15
A116: Capex | B116: =-B115*B111 -> -139.35 | C116: =-C115*C111 -> -144.924 | D116: =-D115*D111 -> -150.72096 | E116: =-E115*E111 -> -156.7498 | F116: =-F115*F111 -> -163.01979 | G116: =-G115*G111 -> -169.54058 | H116: =-H115*H111 -> -176.32221
A117: Tax | B117: =-SUM(B114)*$K$109 -> -102.3758 | C117: =-SUM(C114)*$K$109 -> -106.47083 | D117: =-SUM(D114)*$K$109 -> -110.72967 | E117: =-SUM(E114)*$K$109 -> -115.15885 | F117: =-SUM(F114)*$K$109 -> -119.76521 | G117: =-SUM(G114)*$K$109 -> -124.55581 | H117: =-SUM(H114)*$K$109 -> -129.53805
A118: Operating CF | B118: =SUM(B117,B116,B114) -> 297.0942 | C118: =SUM(C117,C116,C114) -> 308.97797 | D118: =SUM(D117,D116,D114) -> 321.33709 | E118: =SUM(E117,E116,E114) -> 334.19057 | F118: =SUM(F117,F116,F114) -> 347.55819 | G118: =SUM(G117,G116,G114) -> 361.46052 | H118: =SUM(H117,H116,H114) -> 375.91894 | I118: =(H118*(1+L109))/(J109-L109) -> 8376.4547
A119: NPV | B119: =NPV(J109,C118:I118) -> 6792.8785
A120: Currency Adjustment | B120: =B119*1.14 -> 7743.8815
J124: WACC | K124: Tax
J125: 0.062 | K125: 0.31
A126: ANA | B126: 2024 | C126: 2025 | D126: 2026 | E126: 2027 | F126: 2028 | G126: 2029 | H126: 2030 | I126: =H126+1 -> 2031 | J126: =I126+1 -> 2032 | K126: =J126+1 -> 2033 | L126: =K126+1 -> 2034 | M126: =L126+1 -> 2035 | N126: =M126+1 -> 2036 | O126: =N126+1 -> 2037 | P126: =O126+1 -> 2038 | ... AN126: =AM126+1 -> 2062
A127: Revenues | B127: 1315 | C127: =(1+C128)*B127 -> 1354.45 | D127: =(1+D128)*C127 -> 1395.0835 | E127: =(1+E128)*D127 -> 1436.936 | F127: =(1+F128)*E127 -> 1480.0441 | G127: =(1+G128)*F127 -> 1524.4454 | H127: =(1+H128)*G127 -> 1570.1788 | I127: =(1+I128)*H127 -> 1617.2841 | J127: =(1+J128)*I127 -> 1665.8027 | ... AN127: =(1+AN128)*AM127 -> 4043.3403
A128: Growth % | C128: 0.03 | D128: 0.03 | E128: 0.03 | F128: 0.03 | G128: 0.03 | H128: 0.03 | I128: 0.03 | J128: 0.03 | K128: 0.03 | L128: 0.03 | M128: 0.03 | N128: 0.03 | O128: 0.03 | P128: 0.03 | Q128: 0.03 | R128: 0.03 | S128: 0.03 | T128: 0.03 | U128: 0.03 | V128: 0.03 | W128: 0.03 | X128: 0.03 | Y128: 0.03 | Z128: 0.03 | AA128: 0.03 | AB128: 0.03 | AC128: 0.03 | AD128: 0.03 | AE128: 0.03 | AF128: 0.03 | AG128: 0.03 | AH128: 0.03 | AI128: 0.03 | AJ128: 0.03 | AK128: 0.03 | AL128: 0.03 | AM128: 0.03 | AN128: 0.03
A129: EBITDA Margin | B129: 0.67 | C129: 0.67 | D129: 0.67 | E129: 0.67 | F129: 0.67 | G129: 0.67 | H129: 0.67 | I129: 0.67 | J129: 0.67 | K129: 0.67 | L129: 0.67 | M129: 0.67 | N129: 0.67 | O129: 0.67 | P129: 0.67 | Q129: 0.67 | R129: 0.67 | S129: 0.67 | T129: 0.67 | U129: 0.67 | V129: 0.67 | W129: 0.67 | X129: 0.67 | Y129: 0.67 | Z129: 0.67 | AA129: 0.67 | AB129: 0.67 | AC129: 0.67 | AD129: 0.67 | AE129: 0.67 | AF129: 0.67 | AG129: 0.67 | AH129: 0.67 | AI129: 0.67 | AJ129: 0.67 | AK129: 0.67 | AL129: 0.67 | AM129: 0.67 | AN129: 0.67
A130: EBITDA | B130: =B129*B127 -> 881.05 | C130: =C129*C127 -> 907.4815 | D130: =D129*D127 -> 934.70595 | E130: =E129*E127 -> 962.74712 | F130: =F129*F127 -> 991.62954 | G130: =G129*G127 -> 1021.3784 | H130: =H129*H127 -> 1052.0198 | I130: =I129*I127 -> 1083.5804 | ... AN130: =AN129*AN127 -> 2709.038
A131: Capex % of revenue | B131: 0.03 | C131: 0.03 | D131: 0.03 | E131: 0.03 | F131: 0.03 | G131: 0.03 | H131: 0.03 | I131: 0.03 | J131: 0.03 | K131: 0.03 | L131: 0.03 | M131: 0.03 | N131: 0.03 | O131: 0.03 | P131: 0.03 | Q131: 0.03 | R131: 0.03 | S131: 0.03 | T131: 0.03 | U131: 0.03 | V131: 0.03 | W131: 0.03 | X131: 0.03 | Y131: 0.03 | Z131: 0.03 | AA131: 0.03 | AB131: 0.03 | AC131: 0.03 | AD131: 0.03 | AE131: 0.03 | AF131: 0.03 | AG131: 0.03 | AH131: 0.03 | AI131: 0.03 | AJ131: 0.03 | AK131: 0.03 | AL131: 0.03 | AM131: 0.03 | AN131: 0.03
A132: Capex | B132: =-B131*B127 -> -39.45 | C132: =-C131*C127 -> -40.6335 | D132: =-D131*D127 -> -41.852505 | E132: =-E131*E127 -> -43.10808 | F132: =-F131*F127 -> -44.401323 | G132: =-G131*G127 -> -45.733362 | H132: =-H131*H127 -> -47.105363 | I132: =-I131*I127 -> -48.518524 | ... AN132: =-AN131*AN127 -> -121.30021
A133: Tax | B133: =-SUM(B130)*$K$125 -> -273.1255 | C133: =-SUM(C130)*$K$125 -> -281.31927 | D133: =-SUM(D130)*$K$125 -> -289.75884 | E133: =-SUM(E130)*$K$125 -> -298.45161 | F133: =-SUM(F130)*$K$125 -> -307.40516 | G133: =-SUM(G130)*$K$125 -> -316.62731 | H133: =-SUM(H130)*$K$125 -> -326.12613 | I133: =-SUM(I130)*$K$125 -> -335.90991 | ... AN133: =-SUM(AN130)*$K$125 -> -839.80177
A134: Operating CF | B134: =SUM(B133,B132,B130) -> 568.4745 | C134: =SUM(C133,C132,C130) -> 585.52874 | D134: =SUM(D133,D132,D130) -> 603.0946 | E134: =SUM(E133,E132,E130) -> 621.18743 | F134: =SUM(F133,F132,F130) -> 639.82306 | G134: =SUM(G133,G132,G130) -> 659.01775 | H134: =SUM(H133,H132,H130) -> 678.78828 | I134: =SUM(I133,I132,I130) -> 699.15193 | ... AN134: =SUM(AN133,AN132,AN130) -> 1747.936
A135: NPV | B135: =NPV(J125,C134:AN134) -> 12576.652
